{
	"name": "Master_Pipeline",
	"properties": {
		"activities": [
			{
				"name": "Execute Pipeline",
				"type": "ExecutePipeline",
				"dependsOn": [],
				"policy": {
					"secureInput": false
				},
				"userProperties": [],
				"typeProperties": {
					"pipeline": {
						"referenceName": "PL_AzureSQLtoADLSGen2",
						"type": "PipelineReference"
					},
					"waitOnCompletion": true
				}
			},
			{
				"name": "Execute Pipeline1",
				"type": "ExecutePipeline",
				"dependsOn": [
					{
						"activity": "Execute Pipeline",
						"dependencyConditions": [
							"Succeeded"
						]
					}
				],
				"policy": {
					"secureInput": false
				},
				"userProperties": [],
				"typeProperties": {
					"pipeline": {
						"referenceName": "Pl_cust",
						"type": "PipelineReference"
					},
					"waitOnCompletion": true
				}
			},
			{
				"name": "Execute Pipeline1_copy1",
				"type": "ExecutePipeline",
				"dependsOn": [
					{
						"activity": "Execute Pipeline",
						"dependencyConditions": [
							"Succeeded"
						]
					}
				],
				"policy": {
					"secureInput": false
				},
				"userProperties": [],
				"typeProperties": {
					"pipeline": {
						"referenceName": "Pl_orders",
						"type": "PipelineReference"
					},
					"waitOnCompletion": true
				}
			},
			{
				"name": "Execute Pipeline1_copy1_copy1",
				"type": "ExecutePipeline",
				"dependsOn": [
					{
						"activity": "Execute Pipeline",
						"dependencyConditions": [
							"Succeeded"
						]
					}
				],
				"policy": {
					"secureInput": false
				},
				"userProperties": [],
				"typeProperties": {
					"pipeline": {
						"referenceName": "Pl_emp",
						"type": "PipelineReference"
					},
					"waitOnCompletion": true
				}
			},
			{
				"name": "Execute Pipeline1_copy1_copy1_copy1",
				"type": "ExecutePipeline",
				"dependsOn": [
					{
						"activity": "Execute Pipeline",
						"dependencyConditions": [
							"Succeeded"
						]
					}
				],
				"policy": {
					"secureInput": false
				},
				"userProperties": [],
				"typeProperties": {
					"pipeline": {
						"referenceName": "pl_discounts",
						"type": "PipelineReference"
					},
					"waitOnCompletion": true
				}
			},
			{
				"name": "Execute Pipeline1_copy2",
				"type": "ExecutePipeline",
				"dependsOn": [
					{
						"activity": "Execute Pipeline1_copy1",
						"dependencyConditions": [
							"Succeeded"
						]
					},
					{
						"activity": "Execute Pipeline1",
						"dependencyConditions": [
							"Succeeded"
						]
					},
					{
						"activity": "Execute Pipeline1_copy1_copy1",
						"dependencyConditions": [
							"Succeeded"
						]
					},
					{
						"activity": "Execute Pipeline1_copy1_copy1_copy1",
						"dependencyConditions": [
							"Succeeded"
						]
					}
				],
				"policy": {
					"secureInput": false
				},
				"userProperties": [],
				"typeProperties": {
					"pipeline": {
						"referenceName": "loadsilvertogold",
						"type": "PipelineReference"
					},
					"waitOnCompletion": true
				}
			},
			{
				"name": "Execute Pipeline1_copy2_copy1",
				"type": "ExecutePipeline",
				"dependsOn": [
					{
						"activity": "Execute Pipeline1_copy2",
						"dependencyConditions": [
							"Succeeded"
						]
					}
				],
				"policy": {
					"secureInput": false
				},
				"userProperties": [],
				"typeProperties": {
					"pipeline": {
						"referenceName": "loaddata_from_gold_to_DW",
						"type": "PipelineReference"
					},
					"waitOnCompletion": true
				}
			}
		],
		"annotations": [],
		"lastPublishTime": "2026-03-12T16:07:07Z"
	},
	"type": "Microsoft.DataFactory/factories/pipelines"
}